tsso/__init__.py
tsso/admin.py
tsso/apps.py
tsso/middleware.py
tsso/mixins.py
tsso/models.py
tsso/version.py
tsso/views.py
tsso/contrib/__init__.py
tsso/contrib/rest/__init__.py
tsso/contrib/rest/authentication.py
tsso/contrib/tastypie/__init__.py
tsso/contrib/tastypie/authentication.py
tsso/migrations/0001_initial.py
tsso/migrations/__init__.py
django_tsso-0.0.4b1.dist-info/LICENSE
django_tsso-0.0.4b1.dist-info/METADATA
django_tsso-0.0.4b1.dist-info/WHEEL
django_tsso-0.0.4b1.dist-info/top_level.txt
django_tsso-0.0.4b1.dist-info/RECORD
